README.md
setup.py
pulumi_flux/__init__.py
pulumi_flux/_inputs.py
pulumi_flux/_utilities.py
pulumi_flux/flux_bootstrap_git.py
pulumi_flux/get_flux_install.py
pulumi_flux/get_flux_sync.py
pulumi_flux/outputs.py
pulumi_flux/provider.py
pulumi_flux/pulumi-plugin.json
pulumi_flux/py.typed
pulumi_flux.egg-info/PKG-INFO
pulumi_flux.egg-info/SOURCES.txt
pulumi_flux.egg-info/dependency_links.txt
pulumi_flux.egg-info/not-zip-safe
pulumi_flux.egg-info/requires.txt
pulumi_flux.egg-info/top_level.txt
pulumi_flux/config/__init__.py
pulumi_flux/config/outputs.py
pulumi_flux/config/vars.py