Metadata-Version: 2.1
Name: pulumi-flux
Version: 1.0.1
Summary: A Pulumi package for creating and managing Flux cloud resources.
Home-page: https://www.pulumi.com
License: Apache-2.0
Project-URL: Repository, https://github.com/oun/pulumi-flux
Keywords: pulumi flux category/cloud
Platform: UNKNOWN
Requires-Python: >=3.7
